esputnik/__init__.py
esputnik/client.py
esputnik/consts.py
esputnik/esputnik.py
esputnik/exceptions.py
esputnik/templates.py
esputnik/examples/__init__.py
esputnik/examples/cases.py
ok_esputnik-0.3.dist-info/LICENSE
ok_esputnik-0.3.dist-info/METADATA
ok_esputnik-0.3.dist-info/WHEEL
ok_esputnik-0.3.dist-info/top_level.txt
ok_esputnik-0.3.dist-info/RECORD
